mazinsmath/__init__.py
mazinsmath-0.1.0.dist-info/METADATA
mazinsmath-0.1.0.dist-info/WHEEL
mazinsmath-0.1.0.dist-info/top_level.txt
mazinsmath-0.1.0.dist-info/RECORD
