Metadata-Version: 2.4
Name: mazinsmath
Version: 0.1.0
Summary: All-in-one no-imports math toolkit
Requires-Python: >=3.8
